doccano_transformer/__init__.py
doccano_transformer/datasets.py
doccano_transformer/examples.py
doccano_transformer/utils.py
doccano_transformer-1.0.2.dist-info/LICENSE
doccano_transformer-1.0.2.dist-info/METADATA
doccano_transformer-1.0.2.dist-info/WHEEL
doccano_transformer-1.0.2.dist-info/top_level.txt
doccano_transformer-1.0.2.dist-info/RECORD
