Metadata-Version: 2.1
Name: doccano-transformer
Version: 1.0.2
Summary: Format transformer tool for doccano
Home-page: https://github.com/doccano/doccano-transformer
Author: Hiroki Nakayama, Yasufumi Taniguchi
Author-email: hiroki.nakayama.py@gmail.com
License: UNKNOWN
Keywords: doccano,annotation,machine learning
Platform: UNKNOWN
Classifier: Development Status :: 3 - Alpha
Classifier: Intended Audience :: Developers
Classifier: License :: OSI Approved :: MIT License
Classifier: Programming Language :: Python :: 3
Classifier: Programming Language :: Python :: 3.8
Classifier: Programming Language :: Python :: 3 :: Only
Requires-Python: >=3.5, <4
